asyncdb/__init__.py
asyncdb/_sl.py
asyncdb/_sqlfactory_compat.py
asyncdb/aiomysql/__init__.py
asyncdb/aiomysql/config.py
asyncdb/aiomysql/connection.py
asyncdb/aiomysql/error.py
asyncdb/aiomysql/factory.py
asyncdb/aiomysql/observer.py
asyncdb/aiomysql/observers/__init__.py
asyncdb/aiomysql/observers/logging_observer.py
asyncdb/aiomysql/pool.py
asyncdb/aiomysql/result.py
asyncdb/aiomysql/transaction.py
asyncdb/asyncdb.py
asyncdb/context.py
asyncdb/exceptions.py
asyncdb/generics.py
asyncdb/pool.py
asyncdb/py.typed
asyncdb/threadpool.py
gcm_asyncdb-2.3.1.dist-info/METADATA
gcm_asyncdb-2.3.1.dist-info/WHEEL
gcm_asyncdb-2.3.1.dist-info/licenses/LICENSE
gcm_asyncdb-2.3.1.dist-info/RECORD
