Metadata-Version: 2.4
Name: gcm-asyncdb
Version: 2.3.1
Summary: Alternative approach to database API with full native async support and connection pool.
License: MIT
License-File: LICENSE
Author: Michal Kuchta
Author-email: niximor@gmail.com
Requires-Python: >=3.11
Classifier: Development Status :: 5 - Production/Stable
Classifier: Intended Audience :: Developers
Classifier: License :: OSI Approved :: MIT License
Classifier: Operating System :: OS Independent
Classifier: Programming Language :: Python :: 3
Classifier: Programming Language :: Python :: 3.11
Classifier: Programming Language :: Python :: 3.12
Classifier: Programming Language :: Python :: 3.13
Classifier: Programming Language :: Python :: 3.14
Classifier: Programming Language :: SQL
Classifier: Topic :: Database
Classifier: Topic :: Software Development :: Libraries
Requires-Dist: aiomysql (>=0,<1)
Requires-Dist: opentelemetry-api (>=1.39.1,<2.0.0)
Requires-Dist: prometheus-client (>=0,<1)
Requires-Dist: sqlfactory[sqlfactory] (>=1.17.1,<2.0.0)
Requires-Dist: tenacity (>=9.1.2,<10.0.0)
Requires-Dist: typing-extensions (>=4.14.0,<5.0.0)
Requires-Dist: wrapt (>=1,<2)
Project-URL: Documentation, https://asyncdb.gcm.cz/
Project-URL: Homepage, https://gitlab.com/gcm-cz/gcm-asyncdb
Project-URL: Issues, https://gitlab.com/gcm-cz/gcm-asyncdb/-/issues
Project-URL: Repository, https://gitlab.com/gcm-cz/gcm-asyncdb
